CHANGES.rst
LICENSE
MANIFEST.in
README
README.rst
requirements.txt
setup.py
flatkeys/__init__.py
flatkeys.egg-info/PKG-INFO
flatkeys.egg-info/SOURCES.txt
flatkeys.egg-info/dependency_links.txt
flatkeys.egg-info/top_level.txt