Metadata-Version: 1.1
Name: flatkeys
Version: 0.1.0
Summary: flat dictionnaries
Home-page: https://github.com/bfontaine/flatkeys
Author: Baptiste Fontaine
Author-email: b@ptistefontaine.fr
License: Copyright © 2014 – Baptiste Fontaine
